turingscreencli/__init__.py
turingscreencli/__main__.py
turingscreencli/cli.py
turingscreencli/operations.py
turingscreencli/transport.py
turingscreencli-0.1.0.dist-info/licenses/LICENSE
turingscreencli-0.1.0.dist-info/METADATA
turingscreencli-0.1.0.dist-info/WHEEL
turingscreencli-0.1.0.dist-info/entry_points.txt
turingscreencli-0.1.0.dist-info/top_level.txt
turingscreencli-0.1.0.dist-info/RECORD
