Metadata-Version: 2.4
Name: turingscreencli
Version: 0.1.0
Summary: CLI utilities for the Turing Smart Screen 8.8" V1.1 device.
Author: Study Hsueh
License: MIT License
Project-URL: Homepage, https://github.com/phstudy/turing-smart-screen-cli
Project-URL: Issues, https://github.com/phstudy/turing-smart-screen-cli/issues
Keywords: turing,smart-screen,lcd,usb
Classifier: Development Status :: 3 - Alpha
Classifier: Environment :: Console
Classifier: Intended Audience :: System Administrators
Classifier: License :: OSI Approved :: MIT License
Classifier: Operating System :: MacOS
Classifier: Operating System :: POSIX :: Linux
Classifier: Programming Language :: Python
Classifier: Programming Language :: Python :: 3
Classifier: Programming Language :: Python :: 3.9
Classifier: Programming Language :: Python :: 3.10
Classifier: Programming Language :: Python :: 3.11
Classifier: Programming Language :: Python :: 3.12
Classifier: Topic :: System :: Hardware :: Universal Serial Bus (USB)
Requires-Python: >=3.9
License-File: LICENSE
Requires-Dist: pyusb>=1.2.1
Requires-Dist: pycryptodome>=3.15.0
Requires-Dist: Pillow>=9.0.0
Provides-Extra: dev
Requires-Dist: pytest>=7.0.0; extra == "dev"
Requires-Dist: pytest-cov>=4.0.0; extra == "dev"
Requires-Dist: mypy>=1.0.0; extra == "dev"
Requires-Dist: black>=22.0.0; extra == "dev"
Requires-Dist: flake8>=7.1.0; extra == "dev"
Requires-Dist: ruff>=0.5.0; extra == "dev"
Dynamic: license-file
